snlcopyright/__init__.py
snlcopyright/command_line.py
snlcopyright/copyright.txt
snlcopyright/copyright_crud.py
snlcopyright-0.0.12.dist-info/LICENSE
snlcopyright-0.0.12.dist-info/METADATA
snlcopyright-0.0.12.dist-info/WHEEL
snlcopyright-0.0.12.dist-info/entry_points.txt
snlcopyright-0.0.12.dist-info/top_level.txt
snlcopyright-0.0.12.dist-info/RECORD
