Metadata-Version: 2.1
Name: snlcopyright
Version: 0.0.12
Summary: Create, read, update, delete a copyright block in Python source code.
Author-email: Chad Hovey <chovey@sandia.gov>
License: MIT License
Project-URL: Homepage, https://github.com/sandialabs/copyright
Project-URL: Bug Tracker, https://github.com/sandialabs/copyright/issues
Classifier: Programming Language :: Python :: 3
Classifier: License :: OSI Approved :: MIT License
Classifier: Operating System :: OS Independent
Requires-Python: >=3.7
License-File: LICENSE
Requires-Dist: pyyaml
Provides-Extra: dev
Requires-Dist: black (==22.10.0) ; extra == 'dev'
Requires-Dist: flake8 ; extra == 'dev'
Requires-Dist: pytest ; extra == 'dev'
Requires-Dist: pytest-cov ; extra == 'dev'
